LLlib/__init__.py
LLlib/linked_list.py
LLlib/list_node.py
LLlib/utils.py
LLlib-0.0.2.dist-info/LICENSE
LLlib-0.0.2.dist-info/METADATA
LLlib-0.0.2.dist-info/WHEEL
LLlib-0.0.2.dist-info/top_level.txt
LLlib-0.0.2.dist-info/RECORD
