Metadata-Version: 2.1
Name: LLlib
Version: 0.0.2
Summary: A simple Python library for creating linked lists and performing operations.
Home-page: https://github.com/Hnshlr/LinkedListLibrary
Author: Hnshlr
Author-email: hanshaller@outlook.fr
License: MIT
Keywords: linkedlist,listnode,linked list,list node,singly linked list
License-File: LICENSE
